{
    "meta_description": "\"Modern 48in. vanity with quartz top, soft close hinges and slides, 3 doors, 2 drawers, and porcelain sink. Includes backsplash and cabinet hardware. ADA compliant. Made in Vietnam. 1 year warranty.\"",
    "meta_title": "\"Marcello 48\" Free Standing Vanity Set with Cabinet and White Zeus Quartz Vanity Top - Single Hole Faucet Included\"",
    "brand": "James Martin Vanities",
    "uid": "4746710",
    "price": "3002.97",
    "model": "D200-V48-CSN-1WZ",
    "category": "vanities",
    "tables_data": {
        "t1": {
            "Backsplash Height": "4in.",
            "Basin Depth": "4.375in.",
            "Basin Length": "17.125in.",
            "Basin Width": "12in.",
            "Depth": "23.5in.",
            "Height": "37.18in.",
            "Nominal Height": "37in.",
            "Nominal Width": "48in.",
            "Sink Height": "6.875in.",
            "Sink Length": "19.5in.",
            "Sink Width": "14.375in.",
            "Vanity Top Depth": "23.5in.",
            "Vanity Top Width": "48in.",
            "Width": "48in."
        },
        "t2": {
            "Backsplash Included": "Yes",
            "Bridge Drawer Included": "No",
            "Cabinet Hardware Included": "Yes",
            "Faucet Included": "No",
            "Light Included": "No",
            "Medicine Cabinet Included": "No",
            "Mirror Included": "No",
            "Side Cabinet Included": "No",
            "Sidesplash Included": "No",
            "Sink Included": "Yes",
            "USB Port": "No",
            "Vanity Legs Included": "No",
            "Vanity Top Included": "Yes"
        },
        "t3": {
            "Assembly Required": "No",
            "Faucet Holes": "1",
            "Hidden Drawers": "No",
            "Installation Type": "Free Standing",
            "Material": "MDF",
            "Number Of Doors": "3",
            "Number Of Drawers": "2",
            "Number Of Shelves": "2",
            "Self Closing Slides": "No",
            "Sink Material": "Porcelain",
            "Sink Shape": "Rectangular",
            "Soft Close Hinges": "Yes",
            "Soft Close Slides": "Yes",
            "Theme": "Modern",
            "Vanity Top Material": "Quartz"
        },
        "t4": {
            "Electrical Outlet": "No"
        },
        "t5": {
            "ADA": "Yes",
            "Collection": "Marcello",
            "Country Of Origin": "Vietnam",
            "Made in America": "No",
            "Manufacturer Warranty": "1 Year Limited"
        }
    },
    "variants": [
        {
            "img": "products/vanities/K-33579-ASB-1WX/variant/variant_image_6.jpg",
            "color_name": "#DEE2E6"
        },
        {
            "img": "products/vanities/K-33579-ASB-1WX/variant/variant_image_7.jpg",
            "color_name": "#ffffff"
        }
    ],
    "images": [
        "products/vanities/497554/slide/slide_image_1.jpg",
        "products/vanities/D200-V48-CSN-1WZ/slide/slide_image_1.jpg",
        "products/vanities/497554/slide/slide_image_2.jpg",
        "products/vanities/D200-V48-CSN-1WZ/slide/slide_image_2.jpg"
    ],
    "details": "<div class=\"lh-copy H_oFW\">\n <p>\n  <strong>\n   Included Components:\n  </strong>\n </p>\n <ul>\n  <li>\n   Vanity set includes a 3cm eased edge White Zeus Silestone quartz top with matching quartz backsplash, a white porcelain rectangular sink and mounting brackets for easy installation. Top is pre-drilled for single hole faucet. Faucet not included.\n  </li>\n  <li>\n   Covered under 's 1 year limited warranty\n  </li>\n  <li>\n   MDF vanity cabinet with 3 doors, 2 drawers, and 2 shelves\n  </li>\n  <li>\n   Quartz vanity top with porcelain sink and backsplash\n  </li>\n  <li>\n   Faucet is not included and must be purchased separately\n  </li>\n </ul>\n <p>\n  <strong>\n   Cabinet Features:\n  </strong>\n </p>\n <ul>\n  <li>\n   Constructed from MDF providing a lifetime of durability\n  </li>\n  <li>\n   Free standing installation - vanity is seated on the floor with wall anchors, providing a functional design\n  </li>\n  <li>\n   3 door design provides easy access to storage space\n  </li>\n  <li>\n   2 full extension drawers with soft-close slides allows for organized storage\n  </li>\n  <li>\n   Soft close drawer slides operate on smooth ball-bearings and prevent drawers from slamming shut\n  </li>\n  <li>\n   Vanity cabinet includes matching decorative hardware\n  </li>\n  <li>\n   Drawer boxes feature English Dovetail joinery, premium undermount glides, and brushed aluminum laminate drawer liners for easy cleaning.\n  </li>\n  <li>\n   Vanity will ship fully assembled\n  </li>\n </ul>\n <p>\n  <strong>\n   Vanity Top Features:\n  </strong>\n </p>\n <ul>\n  <li>\n   Quartz vanity top includes a sink constructed of porcelain\n  </li>\n  <li>\n   Single pre-drilled faucet hole\n  </li>\n  <li>\n   Each sink features its own rectangular single basin workspace\n  </li>\n  <li>\n   Vanity top includes matching backsplash\n  </li>\n  <li>\n   Faucet sold separately\n  </li>\n </ul>\n <p>\n  <strong>\n   Cabinet Specifications:\n  </strong>\n </p>\n <ul>\n  <li>\n   Number of Doors: 3\n  </li>\n  <li>\n   Number of Drawers: 2\n  </li>\n  <li>\n   Number of Shelves: 2\n  </li>\n </ul>\n <p>\n  <strong>\n   Vanity Top Specifications:\n  </strong>\n </p>\n <ul>\n  <li>\n   Vanity Top Width: 48\" (left edge to right edge)\n  </li>\n  <li>\n   Vanity Top Depth: 23-1/2\" (front edge to back edge)\n  </li>\n  <li>\n   Backsplash Height: 4\"\n  </li>\n  <li>\n   Sink Dimensions: 6-7/8\"H x 14-3/8\"W x 19-1/2\"L\n  </li>\n  <li>\n   Sink Basin Dimensions: 17-1/8\" L x 12\" W x 4-3/8\" D\n  </li>\n  <li>\n   Number of Faucet Holes: 1\n  </li>\n </ul>\n</div>\n"
}